causalkit-0.1.3.dist-info/METADATA
causalkit-0.1.3.dist-info/WHEEL
causalkit-0.1.3.dist-info/license_files/LICENSE
causalkit/__init__.py
causalkit/causalkit.cp312-win_amd64.pyd
causalkit-0.1.3.dist-info/RECORD
