Metadata-Version: 2.3
Name: causalkit
Version: 0.1.3
Classifier: Programming Language :: Rust
Classifier: Programming Language :: Python :: Implementation :: CPython
Classifier: Programming Language :: Python :: Implementation :: PyPy
License-File: LICENSE
Author-email: Xu Wang <scuchina@gmail.com>
Requires-Python: >=3.8
